[
  {
    "id": "bf-109e-3",
    "mode": "arcade",
    "battles": 332373,
    "win_rate": 48.03,
    "avg_kills_per_spawn": 0.981,
    "exp_per_spawn": 81.4,
    "month": "diff_2025_april_may"
  },
  {
    "id": "bf-109e-3",
    "mode": "historical",
    "battles": 218115,
    "win_rate": 47.1,
    "avg_kills_per_spawn": 0.84,
    "exp_per_spawn": 133.4,
    "month": "diff_2025_april_may"
  },
  {
    "id": "bf-109e-3",
    "mode": "simulation",
    "battles": 3862,
    "win_rate": 46.61,
    "avg_kills_per_spawn": 0.564,
    "exp_per_spawn": 83.2,
    "month": "diff_2025_april_may"
  },
  {
    "id": "bf-109e-3",
    "mode": "arcade",
    "battles": 323219,
    "win_rate": 48.19,
    "avg_kills_per_spawn": 1.001,
    "exp_per_spawn": 83.0,
    "month": "diff_2025_august_september"
  },
  {
    "id": "bf-109e-3",
    "mode": "historical",
    "battles": 180641,
    "win_rate": 47.49,
    "avg_kills_per_spawn": 0.867,
    "exp_per_spawn": 137.7,
    "month": "diff_2025_august_september"
  },
  {
    "id": "bf-109e-3",
    "mode": "simulation",
    "battles": 3379,
    "win_rate": 50.99,
    "avg_kills_per_spawn": 0.506,
    "exp_per_spawn": 75.2,
    "month": "diff_2025_august_september"
  },
  {
    "id": "bf-109e-3",
    "mode": "arcade",
    "battles": 152123,
    "win_rate": 48.72,
    "avg_kills_per_spawn": 1.017,
    "exp_per_spawn": 77.0,
    "month": "diff_2025_december_january"
  },
  {
    "id": "bf-109e-3",
    "mode": "historical",
    "battles": 85433,
    "win_rate": 47.38,
    "avg_kills_per_spawn": 0.847,
    "exp_per_spawn": 131.0,
    "month": "diff_2025_december_january"
  },
  {
    "id": "bf-109e-3",
    "mode": "simulation",
    "battles": 1753,
    "win_rate": 45.86,
    "avg_kills_per_spawn": 0.623,
    "exp_per_spawn": 76.0,
    "month": "diff_2025_december_january"
  },
  {
    "id": "bf-109e-3",
    "mode": "arcade",
    "battles": 358834,
    "win_rate": 48.09,
    "avg_kills_per_spawn": 0.974,
    "exp_per_spawn": 80.9,
    "month": "diff_2025_febuary_march"
  },
  {
    "id": "bf-109e-3",
    "mode": "historical",
    "battles": 200920,
    "win_rate": 46.18,
    "avg_kills_per_spawn": 0.81,
    "exp_per_spawn": 132.7,
    "month": "diff_2025_febuary_march"
  },
  {
    "id": "bf-109e-3",
    "mode": "simulation",
    "battles": 3801,
    "win_rate": 46.83,
    "avg_kills_per_spawn": 0.519,
    "exp_per_spawn": 98.1,
    "month": "diff_2025_febuary_march"
  },
  {
    "id": "bf-109e-3",
    "mode": "arcade",
    "battles": 323766,
    "win_rate": 48.25,
    "avg_kills_per_spawn": 1.004,
    "exp_per_spawn": 84.6,
    "month": "diff_2025_july_august"
  },
  {
    "id": "bf-109e-3",
    "mode": "historical",
    "battles": 165135,
    "win_rate": 48.18,
    "avg_kills_per_spawn": 0.84,
    "exp_per_spawn": 134.9,
    "month": "diff_2025_july_august"
  },
  {
    "id": "bf-109e-3",
    "mode": "simulation",
    "battles": 3006,
    "win_rate": 51.16,
    "avg_kills_per_spawn": 0.593,
    "exp_per_spawn": 126.3,
    "month": "diff_2025_july_august"
  },
  {
    "id": "bf-109e-3",
    "mode": "arcade",
    "battles": 338631,
    "win_rate": 48.07,
    "avg_kills_per_spawn": 0.997,
    "exp_per_spawn": 80.7,
    "month": "diff_2025_june_july"
  },
  {
    "id": "bf-109e-3",
    "mode": "historical",
    "battles": 213519,
    "win_rate": 48.18,
    "avg_kills_per_spawn": 0.855,
    "exp_per_spawn": 131.4,
    "month": "diff_2025_june_july"
  },
  {
    "id": "bf-109e-3",
    "mode": "simulation",
    "battles": 3430,
    "win_rate": 48.4,
    "avg_kills_per_spawn": 0.599,
    "exp_per_spawn": 92.4,
    "month": "diff_2025_june_july"
  },
  {
    "id": "bf-109e-3",
    "mode": "arcade",
    "battles": 330341,
    "win_rate": 48.06,
    "avg_kills_per_spawn": 0.966,
    "exp_per_spawn": 78.7,
    "month": "diff_2025_march_april"
  },
  {
    "id": "bf-109e-3",
    "mode": "historical",
    "battles": 190163,
    "win_rate": 46.97,
    "avg_kills_per_spawn": 0.81,
    "exp_per_spawn": 127.3,
    "month": "diff_2025_march_april"
  },
  {
    "id": "bf-109e-3",
    "mode": "simulation",
    "battles": 3884,
    "win_rate": 46.47,
    "avg_kills_per_spawn": 0.588,
    "exp_per_spawn": 97.4,
    "month": "diff_2025_march_april"
  },
  {
    "id": "bf-109e-3",
    "mode": "arcade",
    "battles": 289586,
    "win_rate": 47.8,
    "avg_kills_per_spawn": 0.976,
    "exp_per_spawn": 80.8,
    "month": "diff_2025_may_june"
  },
  {
    "id": "bf-109e-3",
    "mode": "historical",
    "battles": 179635,
    "win_rate": 46.82,
    "avg_kills_per_spawn": 0.846,
    "exp_per_spawn": 136.7,
    "month": "diff_2025_may_june"
  },
  {
    "id": "bf-109e-3",
    "mode": "simulation",
    "battles": 3066,
    "win_rate": 44.1,
    "avg_kills_per_spawn": 0.515,
    "exp_per_spawn": 79.1,
    "month": "diff_2025_may_june"
  },
  {
    "id": "bf-109e-3",
    "mode": "arcade",
    "battles": 184957,
    "win_rate": 48.78,
    "avg_kills_per_spawn": 1.054,
    "exp_per_spawn": 83.0,
    "month": "diff_2025_november_december"
  },
  {
    "id": "bf-109e-3",
    "mode": "historical",
    "battles": 115700,
    "win_rate": 47.19,
    "avg_kills_per_spawn": 0.835,
    "exp_per_spawn": 129.9,
    "month": "diff_2025_november_december"
  },
  {
    "id": "bf-109e-3",
    "mode": "simulation",
    "battles": 2599,
    "win_rate": 48.9,
    "avg_kills_per_spawn": 0.581,
    "exp_per_spawn": 87.8,
    "month": "diff_2025_november_december"
  },
  {
    "id": "bf-109e-3",
    "mode": "arcade",
    "battles": 311937,
    "win_rate": 48.83,
    "avg_kills_per_spawn": 1.102,
    "exp_per_spawn": 79.7,
    "month": "diff_2025_october_november"
  },
  {
    "id": "bf-109e-3",
    "mode": "historical",
    "battles": 131777,
    "win_rate": 47.52,
    "avg_kills_per_spawn": 0.841,
    "exp_per_spawn": 125.3,
    "month": "diff_2025_october_november"
  },
  {
    "id": "bf-109e-3",
    "mode": "simulation",
    "battles": 2818,
    "win_rate": 47.73,
    "avg_kills_per_spawn": 0.596,
    "exp_per_spawn": 83.4,
    "month": "diff_2025_october_november"
  },
  {
    "id": "bf-109e-3",
    "mode": "arcade",
    "battles": 322165,
    "win_rate": 48.36,
    "avg_kills_per_spawn": 1.008,
    "exp_per_spawn": 82.1,
    "month": "diff_2025_september_october"
  },
  {
    "id": "bf-109e-3",
    "mode": "historical",
    "battles": 172208,
    "win_rate": 47.24,
    "avg_kills_per_spawn": 0.851,
    "exp_per_spawn": 133.6,
    "month": "diff_2025_september_october"
  },
  {
    "id": "bf-109e-3",
    "mode": "simulation",
    "battles": 3198,
    "win_rate": 47.69,
    "avg_kills_per_spawn": 0.616,
    "exp_per_spawn": 90.9,
    "month": "diff_2025_september_october"
  },
  {
    "id": "bf-109e-3",
    "mode": "arcade",
    "battles": 176205,
    "win_rate": 48.91,
    "avg_kills_per_spawn": 0.993,
    "exp_per_spawn": 76.5,
    "month": "diff_2026_february_march"
  },
  {
    "id": "bf-109e-3",
    "mode": "historical",
    "battles": 103197,
    "win_rate": 46.0,
    "avg_kills_per_spawn": 0.838,
    "exp_per_spawn": 130.4,
    "month": "diff_2026_february_march"
  },
  {
    "id": "bf-109e-3",
    "mode": "simulation",
    "battles": 2472,
    "win_rate": 47.49,
    "avg_kills_per_spawn": 0.605,
    "exp_per_spawn": 89.5,
    "month": "diff_2026_february_march"
  },
  {
    "id": "bf-109e-3",
    "mode": "arcade",
    "battles": 182399,
    "win_rate": 48.91,
    "avg_kills_per_spawn": 1.019,
    "exp_per_spawn": 78.3,
    "month": "diff_2026_january_february"
  },
  {
    "id": "bf-109e-3",
    "mode": "historical",
    "battles": 111342,
    "win_rate": 47.08,
    "avg_kills_per_spawn": 0.845,
    "exp_per_spawn": 134.4,
    "month": "diff_2026_january_february"
  },
  {
    "id": "bf-109e-3",
    "mode": "simulation",
    "battles": 2682,
    "win_rate": 49.11,
    "avg_kills_per_spawn": 0.61,
    "exp_per_spawn": 93.2,
    "month": "diff_2026_january_february"
  }
]