[
  {
    "id": "fa_18e_block_2",
    "mode": "arcade",
    "battles": 6502,
    "win_rate": 51.55,
    "avg_kills_per_spawn": 1.929,
    "exp_per_spawn": 372.1,
    "month": "diff_2025_december_january"
  },
  {
    "id": "fa_18e_block_2",
    "mode": "historical",
    "battles": 235915,
    "win_rate": 44.88,
    "avg_kills_per_spawn": 0.86,
    "exp_per_spawn": 543.0,
    "month": "diff_2025_december_january"
  },
  {
    "id": "fa_18e_block_2",
    "mode": "simulation",
    "battles": 4821,
    "win_rate": 32.98,
    "avg_kills_per_spawn": 1.056,
    "exp_per_spawn": 148.4,
    "month": "diff_2025_december_january"
  },
  {
    "id": "fa_18e_block_2",
    "mode": "arcade",
    "battles": 28115,
    "win_rate": 53.67,
    "avg_kills_per_spawn": 1.776,
    "exp_per_spawn": 246.1,
    "month": "diff_2026_february_march"
  },
  {
    "id": "fa_18e_block_2",
    "mode": "historical",
    "battles": 323469,
    "win_rate": 49.41,
    "avg_kills_per_spawn": 0.95,
    "exp_per_spawn": 447.0,
    "month": "diff_2026_february_march"
  },
  {
    "id": "fa_18e_block_2",
    "mode": "simulation",
    "battles": 8367,
    "win_rate": 36.46,
    "avg_kills_per_spawn": 1.058,
    "exp_per_spawn": 144.4,
    "month": "diff_2026_february_march"
  },
  {
    "id": "fa_18e_block_2",
    "mode": "arcade",
    "battles": 24261,
    "win_rate": 51.63,
    "avg_kills_per_spawn": 1.743,
    "exp_per_spawn": 276.0,
    "month": "diff_2026_january_february"
  },
  {
    "id": "fa_18e_block_2",
    "mode": "historical",
    "battles": 434845,
    "win_rate": 46.67,
    "avg_kills_per_spawn": 0.914,
    "exp_per_spawn": 466.8,
    "month": "diff_2026_january_february"
  },
  {
    "id": "fa_18e_block_2",
    "mode": "simulation",
    "battles": 11495,
    "win_rate": 38.76,
    "avg_kills_per_spawn": 1.194,
    "exp_per_spawn": 164.7,
    "month": "diff_2026_january_february"
  }
]