[
  {
    "id": "firebrand_tf4",
    "mode": "arcade",
    "battles": 46704,
    "win_rate": 49.73,
    "avg_kills_per_spawn": 1.442,
    "exp_per_spawn": 73.9,
    "month": "diff_2025_april_may"
  },
  {
    "id": "firebrand_tf4",
    "mode": "historical",
    "battles": 40067,
    "win_rate": 52.2,
    "avg_kills_per_spawn": 1.166,
    "exp_per_spawn": 100.0,
    "month": "diff_2025_april_may"
  },
  {
    "id": "firebrand_tf4",
    "mode": "simulation",
    "battles": 348,
    "win_rate": 41.95,
    "avg_kills_per_spawn": 0.417,
    "exp_per_spawn": 39.7,
    "month": "diff_2025_april_may"
  },
  {
    "id": "firebrand_tf4",
    "mode": "arcade",
    "battles": 40329,
    "win_rate": 49.24,
    "avg_kills_per_spawn": 1.337,
    "exp_per_spawn": 74.2,
    "month": "diff_2025_august_september"
  },
  {
    "id": "firebrand_tf4",
    "mode": "historical",
    "battles": 35548,
    "win_rate": 54.36,
    "avg_kills_per_spawn": 1.154,
    "exp_per_spawn": 103.9,
    "month": "diff_2025_august_september"
  },
  {
    "id": "firebrand_tf4",
    "mode": "simulation",
    "battles": 193,
    "win_rate": 41.97,
    "avg_kills_per_spawn": 0.859,
    "exp_per_spawn": 51.1,
    "month": "diff_2025_august_september"
  },
  {
    "id": "firebrand_tf4",
    "mode": "arcade",
    "battles": 23427,
    "win_rate": 49.73,
    "avg_kills_per_spawn": 1.456,
    "exp_per_spawn": 68.8,
    "month": "diff_2025_december_january"
  },
  {
    "id": "firebrand_tf4",
    "mode": "historical",
    "battles": 22295,
    "win_rate": 55.7,
    "avg_kills_per_spawn": 1.164,
    "exp_per_spawn": 97.5,
    "month": "diff_2025_december_january"
  },
  {
    "id": "firebrand_tf4",
    "mode": "simulation",
    "battles": 149,
    "win_rate": 53.02,
    "avg_kills_per_spawn": 0.391,
    "exp_per_spawn": 33.0,
    "month": "diff_2025_december_january"
  },
  {
    "id": "firebrand_tf4",
    "mode": "arcade",
    "battles": 52072,
    "win_rate": 49.7,
    "avg_kills_per_spawn": 1.474,
    "exp_per_spawn": 77.1,
    "month": "diff_2025_febuary_march"
  },
  {
    "id": "firebrand_tf4",
    "mode": "historical",
    "battles": 40637,
    "win_rate": 52.9,
    "avg_kills_per_spawn": 1.184,
    "exp_per_spawn": 108.4,
    "month": "diff_2025_febuary_march"
  },
  {
    "id": "firebrand_tf4",
    "mode": "simulation",
    "battles": 318,
    "win_rate": 41.51,
    "avg_kills_per_spawn": 0.729,
    "exp_per_spawn": 46.7,
    "month": "diff_2025_febuary_march"
  },
  {
    "id": "firebrand_tf4",
    "mode": "arcade",
    "battles": 37472,
    "win_rate": 49.17,
    "avg_kills_per_spawn": 1.31,
    "exp_per_spawn": 76.2,
    "month": "diff_2025_july_august"
  },
  {
    "id": "firebrand_tf4",
    "mode": "historical",
    "battles": 29720,
    "win_rate": 54.84,
    "avg_kills_per_spawn": 1.18,
    "exp_per_spawn": 107.4,
    "month": "diff_2025_july_august"
  },
  {
    "id": "firebrand_tf4",
    "mode": "simulation",
    "battles": 253,
    "win_rate": 44.66,
    "avg_kills_per_spawn": 0.763,
    "exp_per_spawn": 47.2,
    "month": "diff_2025_july_august"
  },
  {
    "id": "firebrand_tf4",
    "mode": "arcade",
    "battles": 46317,
    "win_rate": 49.75,
    "avg_kills_per_spawn": 1.393,
    "exp_per_spawn": 73.4,
    "month": "diff_2025_june_july"
  },
  {
    "id": "firebrand_tf4",
    "mode": "historical",
    "battles": 41428,
    "win_rate": 55.55,
    "avg_kills_per_spawn": 1.174,
    "exp_per_spawn": 104.4,
    "month": "diff_2025_june_july"
  },
  {
    "id": "firebrand_tf4",
    "mode": "simulation",
    "battles": 365,
    "win_rate": 46.85,
    "avg_kills_per_spawn": 0.533,
    "exp_per_spawn": 43.7,
    "month": "diff_2025_june_july"
  },
  {
    "id": "firebrand_tf4",
    "mode": "arcade",
    "battles": 45537,
    "win_rate": 49.58,
    "avg_kills_per_spawn": 1.436,
    "exp_per_spawn": 77.0,
    "month": "diff_2025_march_april"
  },
  {
    "id": "firebrand_tf4",
    "mode": "historical",
    "battles": 34478,
    "win_rate": 52.45,
    "avg_kills_per_spawn": 1.137,
    "exp_per_spawn": 99.2,
    "month": "diff_2025_march_april"
  },
  {
    "id": "firebrand_tf4",
    "mode": "simulation",
    "battles": 234,
    "win_rate": 42.74,
    "avg_kills_per_spawn": 0.578,
    "exp_per_spawn": 47.2,
    "month": "diff_2025_march_april"
  },
  {
    "id": "firebrand_tf4",
    "mode": "arcade",
    "battles": 42145,
    "win_rate": 49.42,
    "avg_kills_per_spawn": 1.455,
    "exp_per_spawn": 76.7,
    "month": "diff_2025_may_june"
  },
  {
    "id": "firebrand_tf4",
    "mode": "historical",
    "battles": 34878,
    "win_rate": 53.2,
    "avg_kills_per_spawn": 1.199,
    "exp_per_spawn": 105.7,
    "month": "diff_2025_may_june"
  },
  {
    "id": "firebrand_tf4",
    "mode": "simulation",
    "battles": 262,
    "win_rate": 43.89,
    "avg_kills_per_spawn": 0.581,
    "exp_per_spawn": 60.9,
    "month": "diff_2025_may_june"
  },
  {
    "id": "firebrand_tf4",
    "mode": "arcade",
    "battles": 32572,
    "win_rate": 49.84,
    "avg_kills_per_spawn": 1.432,
    "exp_per_spawn": 73.2,
    "month": "diff_2025_november_december"
  },
  {
    "id": "firebrand_tf4",
    "mode": "historical",
    "battles": 28760,
    "win_rate": 55.53,
    "avg_kills_per_spawn": 1.155,
    "exp_per_spawn": 99.5,
    "month": "diff_2025_november_december"
  },
  {
    "id": "firebrand_tf4",
    "mode": "simulation",
    "battles": 301,
    "win_rate": 42.52,
    "avg_kills_per_spawn": 0.537,
    "exp_per_spawn": 38.2,
    "month": "diff_2025_november_december"
  },
  {
    "id": "firebrand_tf4",
    "mode": "arcade",
    "battles": 34212,
    "win_rate": 49.6,
    "avg_kills_per_spawn": 1.447,
    "exp_per_spawn": 73.5,
    "month": "diff_2025_october_november"
  },
  {
    "id": "firebrand_tf4",
    "mode": "historical",
    "battles": 29088,
    "win_rate": 55.16,
    "avg_kills_per_spawn": 1.214,
    "exp_per_spawn": 104.3,
    "month": "diff_2025_october_november"
  },
  {
    "id": "firebrand_tf4",
    "mode": "simulation",
    "battles": 234,
    "win_rate": 43.16,
    "avg_kills_per_spawn": 0.465,
    "exp_per_spawn": 51.0,
    "month": "diff_2025_october_november"
  },
  {
    "id": "firebrand_tf4",
    "mode": "arcade",
    "battles": 41372,
    "win_rate": 48.67,
    "avg_kills_per_spawn": 1.344,
    "exp_per_spawn": 75.0,
    "month": "diff_2025_september_october"
  },
  {
    "id": "firebrand_tf4",
    "mode": "historical",
    "battles": 34772,
    "win_rate": 54.26,
    "avg_kills_per_spawn": 1.201,
    "exp_per_spawn": 104.7,
    "month": "diff_2025_september_october"
  },
  {
    "id": "firebrand_tf4",
    "mode": "simulation",
    "battles": 285,
    "win_rate": 41.75,
    "avg_kills_per_spawn": 0.553,
    "exp_per_spawn": 49.4,
    "month": "diff_2025_september_october"
  },
  {
    "id": "firebrand_tf4",
    "mode": "arcade",
    "battles": 28810,
    "win_rate": 50.08,
    "avg_kills_per_spawn": 1.542,
    "exp_per_spawn": 72.1,
    "month": "diff_2026_february_march"
  },
  {
    "id": "firebrand_tf4",
    "mode": "historical",
    "battles": 26198,
    "win_rate": 57.23,
    "avg_kills_per_spawn": 1.186,
    "exp_per_spawn": 104.8,
    "month": "diff_2026_february_march"
  },
  {
    "id": "firebrand_tf4",
    "mode": "simulation",
    "battles": 298,
    "win_rate": 42.62,
    "avg_kills_per_spawn": 0.746,
    "exp_per_spawn": 65.7,
    "month": "diff_2026_february_march"
  },
  {
    "id": "firebrand_tf4",
    "mode": "arcade",
    "battles": 31130,
    "win_rate": 50.61,
    "avg_kills_per_spawn": 1.566,
    "exp_per_spawn": 74.6,
    "month": "diff_2026_january_february"
  },
  {
    "id": "firebrand_tf4",
    "mode": "historical",
    "battles": 30377,
    "win_rate": 56.93,
    "avg_kills_per_spawn": 1.208,
    "exp_per_spawn": 107.3,
    "month": "diff_2026_january_february"
  },
  {
    "id": "firebrand_tf4",
    "mode": "simulation",
    "battles": 282,
    "win_rate": 45.04,
    "avg_kills_per_spawn": 0.697,
    "exp_per_spawn": 37.6,
    "month": "diff_2026_january_february"
  }
]