[
  {
    "id": "germ_battleship_bismarck",
    "mode": "arcade",
    "battles": 12874,
    "win_rate": 51.27,
    "avg_kills_per_spawn": 1.889,
    "exp_per_spawn": 1047.1,
    "month": "diff_2025_august_september"
  },
  {
    "id": "germ_battleship_bismarck",
    "mode": "historical",
    "battles": 5919,
    "win_rate": 54.81,
    "avg_kills_per_spawn": 2.031,
    "exp_per_spawn": 1136.1,
    "month": "diff_2025_august_september"
  },
  {
    "id": "germ_battleship_bismarck",
    "mode": "arcade",
    "battles": 12184,
    "win_rate": 50.16,
    "avg_kills_per_spawn": 1.666,
    "exp_per_spawn": 852.9,
    "month": "diff_2025_december_january"
  },
  {
    "id": "germ_battleship_bismarck",
    "mode": "historical",
    "battles": 4403,
    "win_rate": 50.99,
    "avg_kills_per_spawn": 1.914,
    "exp_per_spawn": 985.2,
    "month": "diff_2025_december_january"
  },
  {
    "id": "germ_battleship_bismarck",
    "mode": "arcade",
    "battles": 10590,
    "win_rate": 52.26,
    "avg_kills_per_spawn": 1.777,
    "exp_per_spawn": 1156.9,
    "month": "diff_2025_july_august"
  },
  {
    "id": "germ_battleship_bismarck",
    "mode": "historical",
    "battles": 8764,
    "win_rate": 53.75,
    "avg_kills_per_spawn": 1.959,
    "exp_per_spawn": 1216.4,
    "month": "diff_2025_july_august"
  },
  {
    "id": "germ_battleship_bismarck",
    "mode": "arcade",
    "battles": 2038,
    "win_rate": 51.32,
    "avg_kills_per_spawn": 1.671,
    "exp_per_spawn": 1200.3,
    "month": "diff_2025_june_july"
  },
  {
    "id": "germ_battleship_bismarck",
    "mode": "historical",
    "battles": 3343,
    "win_rate": 52.47,
    "avg_kills_per_spawn": 1.686,
    "exp_per_spawn": 1232.4,
    "month": "diff_2025_june_july"
  },
  {
    "id": "germ_battleship_bismarck",
    "mode": "arcade",
    "battles": 11781,
    "win_rate": 50.54,
    "avg_kills_per_spawn": 1.771,
    "exp_per_spawn": 947.2,
    "month": "diff_2025_november_december"
  },
  {
    "id": "germ_battleship_bismarck",
    "mode": "historical",
    "battles": 3486,
    "win_rate": 53.59,
    "avg_kills_per_spawn": 1.843,
    "exp_per_spawn": 993.4,
    "month": "diff_2025_november_december"
  },
  {
    "id": "germ_battleship_bismarck",
    "mode": "arcade",
    "battles": 11072,
    "win_rate": 50.32,
    "avg_kills_per_spawn": 1.719,
    "exp_per_spawn": 961.4,
    "month": "diff_2025_october_november"
  },
  {
    "id": "germ_battleship_bismarck",
    "mode": "historical",
    "battles": 3358,
    "win_rate": 55.09,
    "avg_kills_per_spawn": 2.173,
    "exp_per_spawn": 1102.6,
    "month": "diff_2025_october_november"
  },
  {
    "id": "germ_battleship_bismarck",
    "mode": "arcade",
    "battles": 18243,
    "win_rate": 50.63,
    "avg_kills_per_spawn": 1.774,
    "exp_per_spawn": 1025.1,
    "month": "diff_2025_september_october"
  },
  {
    "id": "germ_battleship_bismarck",
    "mode": "historical",
    "battles": 9800,
    "win_rate": 53.2,
    "avg_kills_per_spawn": 1.993,
    "exp_per_spawn": 1092.2,
    "month": "diff_2025_september_october"
  },
  {
    "id": "germ_battleship_bismarck",
    "mode": "arcade",
    "battles": 11074,
    "win_rate": 50.67,
    "avg_kills_per_spawn": 1.997,
    "exp_per_spawn": 837.1,
    "month": "diff_2026_february_march"
  },
  {
    "id": "germ_battleship_bismarck",
    "mode": "historical",
    "battles": 3165,
    "win_rate": 51.47,
    "avg_kills_per_spawn": 2.36,
    "exp_per_spawn": 975.5,
    "month": "diff_2026_february_march"
  },
  {
    "id": "germ_battleship_bismarck",
    "mode": "arcade",
    "battles": 13823,
    "win_rate": 50.1,
    "avg_kills_per_spawn": 1.897,
    "exp_per_spawn": 850.3,
    "month": "diff_2026_january_february"
  },
  {
    "id": "germ_battleship_bismarck",
    "mode": "historical",
    "battles": 4476,
    "win_rate": 53.35,
    "avg_kills_per_spawn": 2.337,
    "exp_per_spawn": 1057.0,
    "month": "diff_2026_january_february"
  }
]