[
  {
    "id": "harrier_frs1_early",
    "mode": "arcade",
    "battles": 6427,
    "win_rate": 50.12,
    "avg_kills_per_spawn": 1.922,
    "exp_per_spawn": 275.9,
    "month": "diff_2025_april_may"
  },
  {
    "id": "harrier_frs1_early",
    "mode": "historical",
    "battles": 14568,
    "win_rate": 49.89,
    "avg_kills_per_spawn": 1.3,
    "exp_per_spawn": 560.7,
    "month": "diff_2025_april_may"
  },
  {
    "id": "harrier_frs1_early",
    "mode": "simulation",
    "battles": 460,
    "win_rate": 57.61,
    "avg_kills_per_spawn": 0.763,
    "exp_per_spawn": 273.8,
    "month": "diff_2025_april_may"
  },
  {
    "id": "harrier_frs1_early",
    "mode": "arcade",
    "battles": 5080,
    "win_rate": 48.46,
    "avg_kills_per_spawn": 1.875,
    "exp_per_spawn": 235.7,
    "month": "diff_2025_august_september"
  },
  {
    "id": "harrier_frs1_early",
    "mode": "historical",
    "battles": 12647,
    "win_rate": 49.51,
    "avg_kills_per_spawn": 1.271,
    "exp_per_spawn": 437.7,
    "month": "diff_2025_august_september"
  },
  {
    "id": "harrier_frs1_early",
    "mode": "simulation",
    "battles": 489,
    "win_rate": 51.53,
    "avg_kills_per_spawn": 1.03,
    "exp_per_spawn": 412.0,
    "month": "diff_2025_august_september"
  },
  {
    "id": "harrier_frs1_early",
    "mode": "arcade",
    "battles": 4868,
    "win_rate": 48.75,
    "avg_kills_per_spawn": 1.807,
    "exp_per_spawn": 248.1,
    "month": "diff_2025_december_january"
  },
  {
    "id": "harrier_frs1_early",
    "mode": "historical",
    "battles": 10430,
    "win_rate": 50.11,
    "avg_kills_per_spawn": 1.258,
    "exp_per_spawn": 529.7,
    "month": "diff_2025_december_january"
  },
  {
    "id": "harrier_frs1_early",
    "mode": "simulation",
    "battles": 276,
    "win_rate": 43.12,
    "avg_kills_per_spawn": 0.528,
    "exp_per_spawn": 503.2,
    "month": "diff_2025_december_january"
  },
  {
    "id": "harrier_frs1_early",
    "mode": "arcade",
    "battles": 8656,
    "win_rate": 48.82,
    "avg_kills_per_spawn": 2.037,
    "exp_per_spawn": 287.8,
    "month": "diff_2025_febuary_march"
  },
  {
    "id": "harrier_frs1_early",
    "mode": "historical",
    "battles": 18547,
    "win_rate": 49.68,
    "avg_kills_per_spawn": 1.14,
    "exp_per_spawn": 565.4,
    "month": "diff_2025_febuary_march"
  },
  {
    "id": "harrier_frs1_early",
    "mode": "simulation",
    "battles": 538,
    "win_rate": 47.77,
    "avg_kills_per_spawn": 0.907,
    "exp_per_spawn": 624.1,
    "month": "diff_2025_febuary_march"
  },
  {
    "id": "harrier_frs1_early",
    "mode": "arcade",
    "battles": 4355,
    "win_rate": 49.64,
    "avg_kills_per_spawn": 2.036,
    "exp_per_spawn": 287.6,
    "month": "diff_2025_july_august"
  },
  {
    "id": "harrier_frs1_early",
    "mode": "historical",
    "battles": 10145,
    "win_rate": 50.91,
    "avg_kills_per_spawn": 1.208,
    "exp_per_spawn": 547.7,
    "month": "diff_2025_july_august"
  },
  {
    "id": "harrier_frs1_early",
    "mode": "simulation",
    "battles": 286,
    "win_rate": 57.34,
    "avg_kills_per_spawn": 0.798,
    "exp_per_spawn": 328.2,
    "month": "diff_2025_july_august"
  },
  {
    "id": "harrier_frs1_early",
    "mode": "arcade",
    "battles": 4421,
    "win_rate": 49.11,
    "avg_kills_per_spawn": 1.913,
    "exp_per_spawn": 254.8,
    "month": "diff_2025_june_july"
  },
  {
    "id": "harrier_frs1_early",
    "mode": "historical",
    "battles": 13050,
    "win_rate": 50.8,
    "avg_kills_per_spawn": 1.228,
    "exp_per_spawn": 534.9,
    "month": "diff_2025_june_july"
  },
  {
    "id": "harrier_frs1_early",
    "mode": "simulation",
    "battles": 376,
    "win_rate": 49.73,
    "avg_kills_per_spawn": 0.824,
    "exp_per_spawn": 358.0,
    "month": "diff_2025_june_july"
  },
  {
    "id": "harrier_frs1_early",
    "mode": "arcade",
    "battles": 6186,
    "win_rate": 49.3,
    "avg_kills_per_spawn": 2.069,
    "exp_per_spawn": 277.1,
    "month": "diff_2025_march_april"
  },
  {
    "id": "harrier_frs1_early",
    "mode": "historical",
    "battles": 13743,
    "win_rate": 49.87,
    "avg_kills_per_spawn": 1.172,
    "exp_per_spawn": 569.7,
    "month": "diff_2025_march_april"
  },
  {
    "id": "harrier_frs1_early",
    "mode": "simulation",
    "battles": 292,
    "win_rate": 52.05,
    "avg_kills_per_spawn": 0.619,
    "exp_per_spawn": 404.6,
    "month": "diff_2025_march_april"
  },
  {
    "id": "harrier_frs1_early",
    "mode": "arcade",
    "battles": 5708,
    "win_rate": 49.47,
    "avg_kills_per_spawn": 2.062,
    "exp_per_spawn": 305.9,
    "month": "diff_2025_may_june"
  },
  {
    "id": "harrier_frs1_early",
    "mode": "historical",
    "battles": 14561,
    "win_rate": 50.09,
    "avg_kills_per_spawn": 1.172,
    "exp_per_spawn": 544.1,
    "month": "diff_2025_may_june"
  },
  {
    "id": "harrier_frs1_early",
    "mode": "simulation",
    "battles": 388,
    "win_rate": 48.45,
    "avg_kills_per_spawn": 0.984,
    "exp_per_spawn": 399.7,
    "month": "diff_2025_may_june"
  },
  {
    "id": "harrier_frs1_early",
    "mode": "arcade",
    "battles": 5937,
    "win_rate": 49.37,
    "avg_kills_per_spawn": 1.974,
    "exp_per_spawn": 235.4,
    "month": "diff_2025_november_december"
  },
  {
    "id": "harrier_frs1_early",
    "mode": "historical",
    "battles": 12458,
    "win_rate": 50.12,
    "avg_kills_per_spawn": 1.325,
    "exp_per_spawn": 542.8,
    "month": "diff_2025_november_december"
  },
  {
    "id": "harrier_frs1_early",
    "mode": "simulation",
    "battles": 470,
    "win_rate": 59.15,
    "avg_kills_per_spawn": 0.79,
    "exp_per_spawn": 484.9,
    "month": "diff_2025_november_december"
  },
  {
    "id": "harrier_frs1_early",
    "mode": "arcade",
    "battles": 5092,
    "win_rate": 47.53,
    "avg_kills_per_spawn": 1.873,
    "exp_per_spawn": 238.3,
    "month": "diff_2025_october_november"
  },
  {
    "id": "harrier_frs1_early",
    "mode": "historical",
    "battles": 12063,
    "win_rate": 47.8,
    "avg_kills_per_spawn": 1.356,
    "exp_per_spawn": 494.0,
    "month": "diff_2025_october_november"
  },
  {
    "id": "harrier_frs1_early",
    "mode": "simulation",
    "battles": 483,
    "win_rate": 49.9,
    "avg_kills_per_spawn": 0.979,
    "exp_per_spawn": 423.1,
    "month": "diff_2025_october_november"
  },
  {
    "id": "harrier_frs1_early",
    "mode": "arcade",
    "battles": 4553,
    "win_rate": 46.19,
    "avg_kills_per_spawn": 1.595,
    "exp_per_spawn": 206.7,
    "month": "diff_2025_september_october"
  },
  {
    "id": "harrier_frs1_early",
    "mode": "historical",
    "battles": 12004,
    "win_rate": 48.74,
    "avg_kills_per_spawn": 1.209,
    "exp_per_spawn": 463.7,
    "month": "diff_2025_september_october"
  },
  {
    "id": "harrier_frs1_early",
    "mode": "simulation",
    "battles": 345,
    "win_rate": 56.23,
    "avg_kills_per_spawn": 0.902,
    "exp_per_spawn": 498.4,
    "month": "diff_2025_september_october"
  },
  {
    "id": "harrier_frs1_early",
    "mode": "arcade",
    "battles": 5582,
    "win_rate": 49.57,
    "avg_kills_per_spawn": 1.83,
    "exp_per_spawn": 225.7,
    "month": "diff_2026_february_march"
  },
  {
    "id": "harrier_frs1_early",
    "mode": "historical",
    "battles": 9908,
    "win_rate": 50.41,
    "avg_kills_per_spawn": 1.568,
    "exp_per_spawn": 526.5,
    "month": "diff_2026_february_march"
  },
  {
    "id": "harrier_frs1_early",
    "mode": "simulation",
    "battles": 280,
    "win_rate": 44.64,
    "avg_kills_per_spawn": 0.689,
    "exp_per_spawn": 318.2,
    "month": "diff_2026_february_march"
  },
  {
    "id": "harrier_frs1_early",
    "mode": "arcade",
    "battles": 6378,
    "win_rate": 49.15,
    "avg_kills_per_spawn": 1.898,
    "exp_per_spawn": 231.7,
    "month": "diff_2026_january_february"
  },
  {
    "id": "harrier_frs1_early",
    "mode": "historical",
    "battles": 10682,
    "win_rate": 49.96,
    "avg_kills_per_spawn": 1.37,
    "exp_per_spawn": 552.3,
    "month": "diff_2026_january_february"
  },
  {
    "id": "harrier_frs1_early",
    "mode": "simulation",
    "battles": 374,
    "win_rate": 48.93,
    "avg_kills_per_spawn": 0.678,
    "exp_per_spawn": 263.9,
    "month": "diff_2026_january_february"
  }
]