[
  {
    "id": "it_c1_ariete_certezza",
    "mode": "arcade",
    "battles": 24858,
    "win_rate": 52.43,
    "avg_kills_per_spawn": 1.53,
    "exp_per_spawn": 1329.4,
    "month": "diff_2025_april_may"
  },
  {
    "id": "it_c1_ariete_certezza",
    "mode": "historical",
    "battles": 205560,
    "win_rate": 53.14,
    "avg_kills_per_spawn": 1.142,
    "exp_per_spawn": 1188.5,
    "month": "diff_2025_april_may"
  },
  {
    "id": "it_c1_ariete_certezza",
    "mode": "simulation",
    "battles": 376,
    "win_rate": 39.1,
    "avg_kills_per_spawn": 0.639,
    "exp_per_spawn": 1170.1,
    "month": "diff_2025_april_may"
  },
  {
    "id": "it_c1_ariete_certezza",
    "mode": "arcade",
    "battles": 9182,
    "win_rate": 52.29,
    "avg_kills_per_spawn": 1.593,
    "exp_per_spawn": 1325.5,
    "month": "diff_2025_august_september"
  },
  {
    "id": "it_c1_ariete_certezza",
    "mode": "historical",
    "battles": 131839,
    "win_rate": 52.96,
    "avg_kills_per_spawn": 1.189,
    "exp_per_spawn": 1187.6,
    "month": "diff_2025_august_september"
  },
  {
    "id": "it_c1_ariete_certezza",
    "mode": "simulation",
    "battles": 490,
    "win_rate": 43.27,
    "avg_kills_per_spawn": 0.733,
    "exp_per_spawn": 1253.3,
    "month": "diff_2025_august_september"
  },
  {
    "id": "it_c1_ariete_certezza",
    "mode": "arcade",
    "battles": 27061,
    "win_rate": 50.71,
    "avg_kills_per_spawn": 1.568,
    "exp_per_spawn": 1306.4,
    "month": "diff_2025_december_january"
  },
  {
    "id": "it_c1_ariete_certezza",
    "mode": "historical",
    "battles": 254413,
    "win_rate": 54.73,
    "avg_kills_per_spawn": 1.229,
    "exp_per_spawn": 1210.8,
    "month": "diff_2025_december_january"
  },
  {
    "id": "it_c1_ariete_certezza",
    "mode": "simulation",
    "battles": 331,
    "win_rate": 40.48,
    "avg_kills_per_spawn": 0.571,
    "exp_per_spawn": 936.2,
    "month": "diff_2025_december_january"
  },
  {
    "id": "it_c1_ariete_certezza",
    "mode": "arcade",
    "battles": 7251,
    "win_rate": 51.0,
    "avg_kills_per_spawn": 1.4,
    "exp_per_spawn": 1133.6,
    "month": "diff_2025_july_august"
  },
  {
    "id": "it_c1_ariete_certezza",
    "mode": "historical",
    "battles": 99497,
    "win_rate": 52.91,
    "avg_kills_per_spawn": 1.12,
    "exp_per_spawn": 1150.2,
    "month": "diff_2025_july_august"
  },
  {
    "id": "it_c1_ariete_certezza",
    "mode": "simulation",
    "battles": 238,
    "win_rate": 49.16,
    "avg_kills_per_spawn": 0.826,
    "exp_per_spawn": 1388.7,
    "month": "diff_2025_july_august"
  },
  {
    "id": "it_c1_ariete_certezza",
    "mode": "arcade",
    "battles": 14258,
    "win_rate": 50.5,
    "avg_kills_per_spawn": 1.357,
    "exp_per_spawn": 1142.6,
    "month": "diff_2025_june_july"
  },
  {
    "id": "it_c1_ariete_certezza",
    "mode": "historical",
    "battles": 165262,
    "win_rate": 53.02,
    "avg_kills_per_spawn": 1.134,
    "exp_per_spawn": 1143.1,
    "month": "diff_2025_june_july"
  },
  {
    "id": "it_c1_ariete_certezza",
    "mode": "simulation",
    "battles": 374,
    "win_rate": 40.11,
    "avg_kills_per_spawn": 0.893,
    "exp_per_spawn": 1329.4,
    "month": "diff_2025_june_july"
  },
  {
    "id": "it_c1_ariete_certezza",
    "mode": "arcade",
    "battles": 10936,
    "win_rate": 53.79,
    "avg_kills_per_spawn": 1.648,
    "exp_per_spawn": 1382.7,
    "month": "diff_2025_march_april"
  },
  {
    "id": "it_c1_ariete_certezza",
    "mode": "historical",
    "battles": 129340,
    "win_rate": 52.11,
    "avg_kills_per_spawn": 1.162,
    "exp_per_spawn": 1189.8,
    "month": "diff_2025_march_april"
  },
  {
    "id": "it_c1_ariete_certezza",
    "mode": "simulation",
    "battles": 227,
    "win_rate": 42.29,
    "avg_kills_per_spawn": 0.607,
    "exp_per_spawn": 1050.4,
    "month": "diff_2025_march_april"
  },
  {
    "id": "it_c1_ariete_certezza",
    "mode": "arcade",
    "battles": 15221,
    "win_rate": 51.36,
    "avg_kills_per_spawn": 1.457,
    "exp_per_spawn": 1238.8,
    "month": "diff_2025_may_june"
  },
  {
    "id": "it_c1_ariete_certezza",
    "mode": "historical",
    "battles": 171246,
    "win_rate": 51.35,
    "avg_kills_per_spawn": 1.097,
    "exp_per_spawn": 1123.2,
    "month": "diff_2025_may_june"
  },
  {
    "id": "it_c1_ariete_certezza",
    "mode": "simulation",
    "battles": 308,
    "win_rate": 43.83,
    "avg_kills_per_spawn": 0.807,
    "exp_per_spawn": 1290.3,
    "month": "diff_2025_may_june"
  },
  {
    "id": "it_c1_ariete_certezza",
    "mode": "arcade",
    "battles": 46546,
    "win_rate": 52.63,
    "avg_kills_per_spawn": 1.692,
    "exp_per_spawn": 1384.8,
    "month": "diff_2025_november_december"
  },
  {
    "id": "it_c1_ariete_certezza",
    "mode": "historical",
    "battles": 462954,
    "win_rate": 53.77,
    "avg_kills_per_spawn": 1.171,
    "exp_per_spawn": 1186.1,
    "month": "diff_2025_november_december"
  },
  {
    "id": "it_c1_ariete_certezza",
    "mode": "simulation",
    "battles": 645,
    "win_rate": 34.57,
    "avg_kills_per_spawn": 0.724,
    "exp_per_spawn": 1095.6,
    "month": "diff_2025_november_december"
  },
  {
    "id": "it_c1_ariete_certezza",
    "mode": "arcade",
    "battles": 16256,
    "win_rate": 53.07,
    "avg_kills_per_spawn": 1.662,
    "exp_per_spawn": 1332.1,
    "month": "diff_2025_october_november"
  },
  {
    "id": "it_c1_ariete_certezza",
    "mode": "historical",
    "battles": 202700,
    "win_rate": 53.21,
    "avg_kills_per_spawn": 1.188,
    "exp_per_spawn": 1184.4,
    "month": "diff_2025_october_november"
  },
  {
    "id": "it_c1_ariete_certezza",
    "mode": "simulation",
    "battles": 282,
    "win_rate": 26.95,
    "avg_kills_per_spawn": 0.805,
    "exp_per_spawn": 1538.8,
    "month": "diff_2025_october_november"
  },
  {
    "id": "it_c1_ariete_certezza",
    "mode": "arcade",
    "battles": 10147,
    "win_rate": 52.15,
    "avg_kills_per_spawn": 1.413,
    "exp_per_spawn": 1190.0,
    "month": "diff_2025_september_october"
  },
  {
    "id": "it_c1_ariete_certezza",
    "mode": "historical",
    "battles": 141881,
    "win_rate": 51.87,
    "avg_kills_per_spawn": 1.176,
    "exp_per_spawn": 1160.6,
    "month": "diff_2025_september_october"
  },
  {
    "id": "it_c1_ariete_certezza",
    "mode": "simulation",
    "battles": 192,
    "win_rate": 42.19,
    "avg_kills_per_spawn": 0.673,
    "exp_per_spawn": 1106.7,
    "month": "diff_2025_september_october"
  },
  {
    "id": "it_c1_ariete_certezza",
    "mode": "arcade",
    "battles": 23066,
    "win_rate": 51.25,
    "avg_kills_per_spawn": 1.514,
    "exp_per_spawn": 1237.3,
    "month": "diff_2026_february_march"
  },
  {
    "id": "it_c1_ariete_certezza",
    "mode": "historical",
    "battles": 210095,
    "win_rate": 50.17,
    "avg_kills_per_spawn": 1.288,
    "exp_per_spawn": 1233.8,
    "month": "diff_2026_february_march"
  },
  {
    "id": "it_c1_ariete_certezza",
    "mode": "simulation",
    "battles": 366,
    "win_rate": 39.34,
    "avg_kills_per_spawn": 0.62,
    "exp_per_spawn": 979.9,
    "month": "diff_2026_february_march"
  },
  {
    "id": "it_c1_ariete_certezza",
    "mode": "arcade",
    "battles": 28013,
    "win_rate": 51.95,
    "avg_kills_per_spawn": 1.62,
    "exp_per_spawn": 1328.3,
    "month": "diff_2026_january_february"
  },
  {
    "id": "it_c1_ariete_certezza",
    "mode": "historical",
    "battles": 273630,
    "win_rate": 52.85,
    "avg_kills_per_spawn": 1.279,
    "exp_per_spawn": 1230.7,
    "month": "diff_2026_january_february"
  },
  {
    "id": "it_c1_ariete_certezza",
    "mode": "simulation",
    "battles": 475,
    "win_rate": 37.89,
    "avg_kills_per_spawn": 0.678,
    "exp_per_spawn": 1049.6,
    "month": "diff_2026_january_february"
  }
]