[
  {
    "id": "jp_battlecruiser_kongo",
    "mode": "arcade",
    "battles": 3469,
    "win_rate": 51.02,
    "avg_kills_per_spawn": 1.342,
    "exp_per_spawn": 756.9,
    "month": "diff_2025_april_may"
  },
  {
    "id": "jp_battlecruiser_kongo",
    "mode": "historical",
    "battles": 1909,
    "win_rate": 48.98,
    "avg_kills_per_spawn": 1.727,
    "exp_per_spawn": 1079.1,
    "month": "diff_2025_april_may"
  },
  {
    "id": "jp_battlecruiser_kongo",
    "mode": "arcade",
    "battles": 5165,
    "win_rate": 48.4,
    "avg_kills_per_spawn": 1.317,
    "exp_per_spawn": 866.0,
    "month": "diff_2025_august_september"
  },
  {
    "id": "jp_battlecruiser_kongo",
    "mode": "historical",
    "battles": 2260,
    "win_rate": 47.26,
    "avg_kills_per_spawn": 1.362,
    "exp_per_spawn": 1023.3,
    "month": "diff_2025_august_september"
  },
  {
    "id": "jp_battlecruiser_kongo",
    "mode": "arcade",
    "battles": 5365,
    "win_rate": 47.77,
    "avg_kills_per_spawn": 1.403,
    "exp_per_spawn": 769.9,
    "month": "diff_2025_december_january"
  },
  {
    "id": "jp_battlecruiser_kongo",
    "mode": "historical",
    "battles": 1580,
    "win_rate": 47.91,
    "avg_kills_per_spawn": 1.452,
    "exp_per_spawn": 853.8,
    "month": "diff_2025_december_january"
  },
  {
    "id": "jp_battlecruiser_kongo",
    "mode": "arcade",
    "battles": 2626,
    "win_rate": 48.4,
    "avg_kills_per_spawn": 1.096,
    "exp_per_spawn": 650.0,
    "month": "diff_2025_febuary_march"
  },
  {
    "id": "jp_battlecruiser_kongo",
    "mode": "historical",
    "battles": 1601,
    "win_rate": 49.97,
    "avg_kills_per_spawn": 1.515,
    "exp_per_spawn": 974.1,
    "month": "diff_2025_febuary_march"
  },
  {
    "id": "jp_battlecruiser_kongo",
    "mode": "arcade",
    "battles": 5485,
    "win_rate": 48.02,
    "avg_kills_per_spawn": 1.165,
    "exp_per_spawn": 805.6,
    "month": "diff_2025_july_august"
  },
  {
    "id": "jp_battlecruiser_kongo",
    "mode": "historical",
    "battles": 4118,
    "win_rate": 48.93,
    "avg_kills_per_spawn": 1.184,
    "exp_per_spawn": 946.3,
    "month": "diff_2025_july_august"
  },
  {
    "id": "jp_battlecruiser_kongo",
    "mode": "arcade",
    "battles": 8750,
    "win_rate": 48.9,
    "avg_kills_per_spawn": 1.226,
    "exp_per_spawn": 795.1,
    "month": "diff_2025_june_july"
  },
  {
    "id": "jp_battlecruiser_kongo",
    "mode": "historical",
    "battles": 8666,
    "win_rate": 48.71,
    "avg_kills_per_spawn": 1.36,
    "exp_per_spawn": 1096.2,
    "month": "diff_2025_june_july"
  },
  {
    "id": "jp_battlecruiser_kongo",
    "mode": "arcade",
    "battles": 3195,
    "win_rate": 47.7,
    "avg_kills_per_spawn": 1.065,
    "exp_per_spawn": 673.4,
    "month": "diff_2025_march_april"
  },
  {
    "id": "jp_battlecruiser_kongo",
    "mode": "historical",
    "battles": 2094,
    "win_rate": 45.27,
    "avg_kills_per_spawn": 1.024,
    "exp_per_spawn": 824.1,
    "month": "diff_2025_march_april"
  },
  {
    "id": "jp_battlecruiser_kongo",
    "mode": "arcade",
    "battles": 3776,
    "win_rate": 49.15,
    "avg_kills_per_spawn": 1.41,
    "exp_per_spawn": 843.0,
    "month": "diff_2025_may_june"
  },
  {
    "id": "jp_battlecruiser_kongo",
    "mode": "historical",
    "battles": 2623,
    "win_rate": 49.29,
    "avg_kills_per_spawn": 1.708,
    "exp_per_spawn": 1162.0,
    "month": "diff_2025_may_june"
  },
  {
    "id": "jp_battlecruiser_kongo",
    "mode": "arcade",
    "battles": 5526,
    "win_rate": 48.23,
    "avg_kills_per_spawn": 1.333,
    "exp_per_spawn": 802.9,
    "month": "diff_2025_november_december"
  },
  {
    "id": "jp_battlecruiser_kongo",
    "mode": "historical",
    "battles": 1772,
    "win_rate": 49.38,
    "avg_kills_per_spawn": 1.315,
    "exp_per_spawn": 933.9,
    "month": "diff_2025_november_december"
  },
  {
    "id": "jp_battlecruiser_kongo",
    "mode": "arcade",
    "battles": 6076,
    "win_rate": 47.91,
    "avg_kills_per_spawn": 1.524,
    "exp_per_spawn": 858.5,
    "month": "diff_2025_october_november"
  },
  {
    "id": "jp_battlecruiser_kongo",
    "mode": "historical",
    "battles": 2087,
    "win_rate": 47.92,
    "avg_kills_per_spawn": 1.43,
    "exp_per_spawn": 964.6,
    "month": "diff_2025_october_november"
  },
  {
    "id": "jp_battlecruiser_kongo",
    "mode": "arcade",
    "battles": 9083,
    "win_rate": 48.0,
    "avg_kills_per_spawn": 1.263,
    "exp_per_spawn": 751.7,
    "month": "diff_2025_september_october"
  },
  {
    "id": "jp_battlecruiser_kongo",
    "mode": "historical",
    "battles": 3790,
    "win_rate": 51.42,
    "avg_kills_per_spawn": 1.273,
    "exp_per_spawn": 895.1,
    "month": "diff_2025_september_october"
  },
  {
    "id": "jp_battlecruiser_kongo",
    "mode": "arcade",
    "battles": 3711,
    "win_rate": 48.02,
    "avg_kills_per_spawn": 1.75,
    "exp_per_spawn": 679.2,
    "month": "diff_2026_february_march"
  },
  {
    "id": "jp_battlecruiser_kongo",
    "mode": "historical",
    "battles": 796,
    "win_rate": 47.24,
    "avg_kills_per_spawn": 1.861,
    "exp_per_spawn": 865.7,
    "month": "diff_2026_february_march"
  },
  {
    "id": "jp_battlecruiser_kongo",
    "mode": "arcade",
    "battles": 4992,
    "win_rate": 48.54,
    "avg_kills_per_spawn": 1.645,
    "exp_per_spawn": 782.1,
    "month": "diff_2026_january_february"
  },
  {
    "id": "jp_battlecruiser_kongo",
    "mode": "historical",
    "battles": 1757,
    "win_rate": 49.8,
    "avg_kills_per_spawn": 1.765,
    "exp_per_spawn": 835.4,
    "month": "diff_2026_january_february"
  }
]