[
  {
    "id": "us_m2a4",
    "mode": "arcade",
    "battles": 375947,
    "win_rate": 49.99,
    "avg_kills_per_spawn": 0.896,
    "exp_per_spawn": 121.8,
    "month": "diff_2025_april_may"
  },
  {
    "id": "us_m2a4",
    "mode": "historical",
    "battles": 288449,
    "win_rate": 43.38,
    "avg_kills_per_spawn": 0.834,
    "exp_per_spawn": 157.0,
    "month": "diff_2025_april_may"
  },
  {
    "id": "us_m2a4",
    "mode": "simulation",
    "battles": 387,
    "win_rate": 41.09,
    "avg_kills_per_spawn": 0.482,
    "exp_per_spawn": 149.8,
    "month": "diff_2025_april_may"
  },
  {
    "id": "us_m2a4",
    "mode": "arcade",
    "battles": 725282,
    "win_rate": 59.04,
    "avg_kills_per_spawn": 1.19,
    "exp_per_spawn": 94.9,
    "month": "diff_2025_august_september"
  },
  {
    "id": "us_m2a4",
    "mode": "historical",
    "battles": 351119,
    "win_rate": 44.57,
    "avg_kills_per_spawn": 0.803,
    "exp_per_spawn": 145.7,
    "month": "diff_2025_august_september"
  },
  {
    "id": "us_m2a4",
    "mode": "simulation",
    "battles": 549,
    "win_rate": 35.88,
    "avg_kills_per_spawn": 0.449,
    "exp_per_spawn": 138.4,
    "month": "diff_2025_august_september"
  },
  {
    "id": "us_m2a4",
    "mode": "arcade",
    "battles": 424389,
    "win_rate": 64.17,
    "avg_kills_per_spawn": 1.32,
    "exp_per_spawn": 80.5,
    "month": "diff_2025_december_january"
  },
  {
    "id": "us_m2a4",
    "mode": "historical",
    "battles": 166577,
    "win_rate": 44.65,
    "avg_kills_per_spawn": 0.762,
    "exp_per_spawn": 137.2,
    "month": "diff_2025_december_january"
  },
  {
    "id": "us_m2a4",
    "mode": "simulation",
    "battles": 312,
    "win_rate": 31.09,
    "avg_kills_per_spawn": 0.354,
    "exp_per_spawn": 134.9,
    "month": "diff_2025_december_january"
  },
  {
    "id": "us_m2a4",
    "mode": "arcade",
    "battles": 672193,
    "win_rate": 58.72,
    "avg_kills_per_spawn": 1.204,
    "exp_per_spawn": 101.1,
    "month": "diff_2025_febuary_march"
  },
  {
    "id": "us_m2a4",
    "mode": "historical",
    "battles": 341374,
    "win_rate": 43.54,
    "avg_kills_per_spawn": 0.8,
    "exp_per_spawn": 151.6,
    "month": "diff_2025_febuary_march"
  },
  {
    "id": "us_m2a4",
    "mode": "simulation",
    "battles": 520,
    "win_rate": 41.92,
    "avg_kills_per_spawn": 0.429,
    "exp_per_spawn": 160.0,
    "month": "diff_2025_febuary_march"
  },
  {
    "id": "us_m2a4",
    "mode": "arcade",
    "battles": 762195,
    "win_rate": 58.85,
    "avg_kills_per_spawn": 1.15,
    "exp_per_spawn": 89.4,
    "month": "diff_2025_july_august"
  },
  {
    "id": "us_m2a4",
    "mode": "historical",
    "battles": 342004,
    "win_rate": 43.72,
    "avg_kills_per_spawn": 0.756,
    "exp_per_spawn": 139.9,
    "month": "diff_2025_july_august"
  },
  {
    "id": "us_m2a4",
    "mode": "simulation",
    "battles": 504,
    "win_rate": 35.12,
    "avg_kills_per_spawn": 0.417,
    "exp_per_spawn": 134.5,
    "month": "diff_2025_july_august"
  },
  {
    "id": "us_m2a4",
    "mode": "arcade",
    "battles": 699467,
    "win_rate": 57.91,
    "avg_kills_per_spawn": 1.137,
    "exp_per_spawn": 93.8,
    "month": "diff_2025_june_july"
  },
  {
    "id": "us_m2a4",
    "mode": "historical",
    "battles": 367765,
    "win_rate": 43.37,
    "avg_kills_per_spawn": 0.787,
    "exp_per_spawn": 146.7,
    "month": "diff_2025_june_july"
  },
  {
    "id": "us_m2a4",
    "mode": "simulation",
    "battles": 502,
    "win_rate": 32.07,
    "avg_kills_per_spawn": 0.348,
    "exp_per_spawn": 109.9,
    "month": "diff_2025_june_july"
  },
  {
    "id": "us_m2a4",
    "mode": "arcade",
    "battles": 367018,
    "win_rate": 50.56,
    "avg_kills_per_spawn": 0.894,
    "exp_per_spawn": 115.4,
    "month": "diff_2025_march_april"
  },
  {
    "id": "us_m2a4",
    "mode": "historical",
    "battles": 273786,
    "win_rate": 42.39,
    "avg_kills_per_spawn": 0.812,
    "exp_per_spawn": 152.9,
    "month": "diff_2025_march_april"
  },
  {
    "id": "us_m2a4",
    "mode": "simulation",
    "battles": 371,
    "win_rate": 37.2,
    "avg_kills_per_spawn": 0.475,
    "exp_per_spawn": 159.7,
    "month": "diff_2025_march_april"
  },
  {
    "id": "us_m2a4",
    "mode": "arcade",
    "battles": 626580,
    "win_rate": 58.39,
    "avg_kills_per_spawn": 1.153,
    "exp_per_spawn": 93.5,
    "month": "diff_2025_may_june"
  },
  {
    "id": "us_m2a4",
    "mode": "historical",
    "battles": 319113,
    "win_rate": 43.61,
    "avg_kills_per_spawn": 0.766,
    "exp_per_spawn": 144.9,
    "month": "diff_2025_may_june"
  },
  {
    "id": "us_m2a4",
    "mode": "simulation",
    "battles": 446,
    "win_rate": 39.69,
    "avg_kills_per_spawn": 0.403,
    "exp_per_spawn": 144.6,
    "month": "diff_2025_may_june"
  },
  {
    "id": "us_m2a4",
    "mode": "arcade",
    "battles": 196209,
    "win_rate": 50.04,
    "avg_kills_per_spawn": 0.905,
    "exp_per_spawn": 124.6,
    "month": "diff_2025_november_december"
  },
  {
    "id": "us_m2a4",
    "mode": "historical",
    "battles": 174960,
    "win_rate": 45.88,
    "avg_kills_per_spawn": 0.938,
    "exp_per_spawn": 166.9,
    "month": "diff_2025_november_december"
  },
  {
    "id": "us_m2a4",
    "mode": "simulation",
    "battles": 266,
    "win_rate": 38.35,
    "avg_kills_per_spawn": 0.526,
    "exp_per_spawn": 137.9,
    "month": "diff_2025_november_december"
  },
  {
    "id": "us_m2a4",
    "mode": "arcade",
    "battles": 595535,
    "win_rate": 49.89,
    "avg_kills_per_spawn": 0.854,
    "exp_per_spawn": 115.6,
    "month": "diff_2025_october_november"
  },
  {
    "id": "us_m2a4",
    "mode": "historical",
    "battles": 270353,
    "win_rate": 42.66,
    "avg_kills_per_spawn": 0.836,
    "exp_per_spawn": 152.0,
    "month": "diff_2025_october_november"
  },
  {
    "id": "us_m2a4",
    "mode": "simulation",
    "battles": 409,
    "win_rate": 35.21,
    "avg_kills_per_spawn": 0.383,
    "exp_per_spawn": 146.7,
    "month": "diff_2025_october_november"
  },
  {
    "id": "us_m2a4",
    "mode": "arcade",
    "battles": 671853,
    "win_rate": 57.86,
    "avg_kills_per_spawn": 1.147,
    "exp_per_spawn": 94.2,
    "month": "diff_2025_september_october"
  },
  {
    "id": "us_m2a4",
    "mode": "historical",
    "battles": 330636,
    "win_rate": 44.28,
    "avg_kills_per_spawn": 0.799,
    "exp_per_spawn": 145.6,
    "month": "diff_2025_september_october"
  },
  {
    "id": "us_m2a4",
    "mode": "simulation",
    "battles": 546,
    "win_rate": 43.77,
    "avg_kills_per_spawn": 0.363,
    "exp_per_spawn": 119.1,
    "month": "diff_2025_september_october"
  },
  {
    "id": "us_m2a4",
    "mode": "arcade",
    "battles": 407603,
    "win_rate": 60.3,
    "avg_kills_per_spawn": 1.207,
    "exp_per_spawn": 86.9,
    "month": "diff_2026_february_march"
  },
  {
    "id": "us_m2a4",
    "mode": "historical",
    "battles": 186836,
    "win_rate": 46.16,
    "avg_kills_per_spawn": 0.841,
    "exp_per_spawn": 148.0,
    "month": "diff_2026_february_march"
  },
  {
    "id": "us_m2a4",
    "mode": "simulation",
    "battles": 314,
    "win_rate": 33.76,
    "avg_kills_per_spawn": 0.42,
    "exp_per_spawn": 130.7,
    "month": "diff_2026_february_march"
  },
  {
    "id": "us_m2a4",
    "mode": "arcade",
    "battles": 381268,
    "win_rate": 58.7,
    "avg_kills_per_spawn": 1.146,
    "exp_per_spawn": 92.8,
    "month": "diff_2026_january_february"
  },
  {
    "id": "us_m2a4",
    "mode": "historical",
    "battles": 200854,
    "win_rate": 45.44,
    "avg_kills_per_spawn": 0.855,
    "exp_per_spawn": 153.0,
    "month": "diff_2026_january_february"
  },
  {
    "id": "us_m2a4",
    "mode": "simulation",
    "battles": 402,
    "win_rate": 29.85,
    "avg_kills_per_spawn": 0.44,
    "exp_per_spawn": 157.9,
    "month": "diff_2026_january_february"
  }
]