[
  {
    "id": "ussr_t_34_1941_57",
    "mode": "arcade",
    "battles": 896518,
    "win_rate": 47.41,
    "avg_kills_per_spawn": 0.79,
    "exp_per_spawn": 159.7,
    "month": "diff_2025_april_may"
  },
  {
    "id": "ussr_t_34_1941_57",
    "mode": "historical",
    "battles": 1398853,
    "win_rate": 47.99,
    "avg_kills_per_spawn": 0.767,
    "exp_per_spawn": 196.9,
    "month": "diff_2025_april_may"
  },
  {
    "id": "ussr_t_34_1941_57",
    "mode": "simulation",
    "battles": 7090,
    "win_rate": 47.66,
    "avg_kills_per_spawn": 0.874,
    "exp_per_spawn": 259.6,
    "month": "diff_2025_april_may"
  },
  {
    "id": "ussr_t_34_1941_57",
    "mode": "arcade",
    "battles": 783953,
    "win_rate": 46.95,
    "avg_kills_per_spawn": 0.762,
    "exp_per_spawn": 152.1,
    "month": "diff_2025_august_september"
  },
  {
    "id": "ussr_t_34_1941_57",
    "mode": "historical",
    "battles": 1313944,
    "win_rate": 45.21,
    "avg_kills_per_spawn": 0.757,
    "exp_per_spawn": 189.9,
    "month": "diff_2025_august_september"
  },
  {
    "id": "ussr_t_34_1941_57",
    "mode": "simulation",
    "battles": 6334,
    "win_rate": 54.03,
    "avg_kills_per_spawn": 0.971,
    "exp_per_spawn": 278.8,
    "month": "diff_2025_august_september"
  },
  {
    "id": "ussr_t_34_1941_57",
    "mode": "arcade",
    "battles": 486740,
    "win_rate": 47.74,
    "avg_kills_per_spawn": 0.872,
    "exp_per_spawn": 166.9,
    "month": "diff_2025_december_january"
  },
  {
    "id": "ussr_t_34_1941_57",
    "mode": "historical",
    "battles": 601309,
    "win_rate": 46.25,
    "avg_kills_per_spawn": 0.832,
    "exp_per_spawn": 199.4,
    "month": "diff_2025_december_january"
  },
  {
    "id": "ussr_t_34_1941_57",
    "mode": "simulation",
    "battles": 5814,
    "win_rate": 56.79,
    "avg_kills_per_spawn": 0.944,
    "exp_per_spawn": 259.5,
    "month": "diff_2025_december_january"
  },
  {
    "id": "ussr_t_34_1941_57",
    "mode": "arcade",
    "battles": 891273,
    "win_rate": 47.19,
    "avg_kills_per_spawn": 0.767,
    "exp_per_spawn": 161.2,
    "month": "diff_2025_febuary_march"
  },
  {
    "id": "ussr_t_34_1941_57",
    "mode": "historical",
    "battles": 1302547,
    "win_rate": 47.13,
    "avg_kills_per_spawn": 0.759,
    "exp_per_spawn": 199.9,
    "month": "diff_2025_febuary_march"
  },
  {
    "id": "ussr_t_34_1941_57",
    "mode": "simulation",
    "battles": 7666,
    "win_rate": 44.0,
    "avg_kills_per_spawn": 0.861,
    "exp_per_spawn": 273.4,
    "month": "diff_2025_febuary_march"
  },
  {
    "id": "ussr_t_34_1941_57",
    "mode": "arcade",
    "battles": 772617,
    "win_rate": 47.24,
    "avg_kills_per_spawn": 0.764,
    "exp_per_spawn": 154.2,
    "month": "diff_2025_july_august"
  },
  {
    "id": "ussr_t_34_1941_57",
    "mode": "historical",
    "battles": 1176213,
    "win_rate": 44.94,
    "avg_kills_per_spawn": 0.735,
    "exp_per_spawn": 188.8,
    "month": "diff_2025_july_august"
  },
  {
    "id": "ussr_t_34_1941_57",
    "mode": "simulation",
    "battles": 5920,
    "win_rate": 55.84,
    "avg_kills_per_spawn": 0.933,
    "exp_per_spawn": 273.7,
    "month": "diff_2025_july_august"
  },
  {
    "id": "ussr_t_34_1941_57",
    "mode": "arcade",
    "battles": 903456,
    "win_rate": 47.12,
    "avg_kills_per_spawn": 0.769,
    "exp_per_spawn": 154.4,
    "month": "diff_2025_june_july"
  },
  {
    "id": "ussr_t_34_1941_57",
    "mode": "historical",
    "battles": 1516081,
    "win_rate": 44.59,
    "avg_kills_per_spawn": 0.748,
    "exp_per_spawn": 191.2,
    "month": "diff_2025_june_july"
  },
  {
    "id": "ussr_t_34_1941_57",
    "mode": "simulation",
    "battles": 6457,
    "win_rate": 56.02,
    "avg_kills_per_spawn": 0.913,
    "exp_per_spawn": 265.3,
    "month": "diff_2025_june_july"
  },
  {
    "id": "ussr_t_34_1941_57",
    "mode": "arcade",
    "battles": 860720,
    "win_rate": 47.14,
    "avg_kills_per_spawn": 0.761,
    "exp_per_spawn": 155.6,
    "month": "diff_2025_march_april"
  },
  {
    "id": "ussr_t_34_1941_57",
    "mode": "historical",
    "battles": 1289775,
    "win_rate": 47.22,
    "avg_kills_per_spawn": 0.756,
    "exp_per_spawn": 194.8,
    "month": "diff_2025_march_april"
  },
  {
    "id": "ussr_t_34_1941_57",
    "mode": "simulation",
    "battles": 8143,
    "win_rate": 46.29,
    "avg_kills_per_spawn": 0.847,
    "exp_per_spawn": 266.8,
    "month": "diff_2025_march_april"
  },
  {
    "id": "ussr_t_34_1941_57",
    "mode": "arcade",
    "battles": 948445,
    "win_rate": 47.28,
    "avg_kills_per_spawn": 0.791,
    "exp_per_spawn": 165.3,
    "month": "diff_2025_may_june"
  },
  {
    "id": "ussr_t_34_1941_57",
    "mode": "historical",
    "battles": 1542276,
    "win_rate": 48.79,
    "avg_kills_per_spawn": 0.773,
    "exp_per_spawn": 207.7,
    "month": "diff_2025_may_june"
  },
  {
    "id": "ussr_t_34_1941_57",
    "mode": "simulation",
    "battles": 6058,
    "win_rate": 56.14,
    "avg_kills_per_spawn": 0.912,
    "exp_per_spawn": 279.4,
    "month": "diff_2025_may_june"
  },
  {
    "id": "ussr_t_34_1941_57",
    "mode": "arcade",
    "battles": 546383,
    "win_rate": 47.58,
    "avg_kills_per_spawn": 0.859,
    "exp_per_spawn": 167.0,
    "month": "diff_2025_november_december"
  },
  {
    "id": "ussr_t_34_1941_57",
    "mode": "historical",
    "battles": 840764,
    "win_rate": 47.36,
    "avg_kills_per_spawn": 0.826,
    "exp_per_spawn": 197.8,
    "month": "diff_2025_november_december"
  },
  {
    "id": "ussr_t_34_1941_57",
    "mode": "simulation",
    "battles": 6565,
    "win_rate": 54.9,
    "avg_kills_per_spawn": 1.007,
    "exp_per_spawn": 273.7,
    "month": "diff_2025_november_december"
  },
  {
    "id": "ussr_t_34_1941_57",
    "mode": "arcade",
    "battles": 604713,
    "win_rate": 47.56,
    "avg_kills_per_spawn": 0.816,
    "exp_per_spawn": 159.0,
    "month": "diff_2025_october_november"
  },
  {
    "id": "ussr_t_34_1941_57",
    "mode": "historical",
    "battles": 945965,
    "win_rate": 46.26,
    "avg_kills_per_spawn": 0.779,
    "exp_per_spawn": 189.9,
    "month": "diff_2025_october_november"
  },
  {
    "id": "ussr_t_34_1941_57",
    "mode": "simulation",
    "battles": 4194,
    "win_rate": 62.11,
    "avg_kills_per_spawn": 0.97,
    "exp_per_spawn": 281.6,
    "month": "diff_2025_october_november"
  },
  {
    "id": "ussr_t_34_1941_57",
    "mode": "arcade",
    "battles": 770183,
    "win_rate": 47.14,
    "avg_kills_per_spawn": 0.79,
    "exp_per_spawn": 155.1,
    "month": "diff_2025_september_october"
  },
  {
    "id": "ussr_t_34_1941_57",
    "mode": "historical",
    "battles": 1175441,
    "win_rate": 45.79,
    "avg_kills_per_spawn": 0.752,
    "exp_per_spawn": 188.0,
    "month": "diff_2025_september_october"
  },
  {
    "id": "ussr_t_34_1941_57",
    "mode": "simulation",
    "battles": 5395,
    "win_rate": 55.83,
    "avg_kills_per_spawn": 0.986,
    "exp_per_spawn": 280.9,
    "month": "diff_2025_september_october"
  },
  {
    "id": "ussr_t_34_1941_57",
    "mode": "arcade",
    "battles": 494542,
    "win_rate": 47.86,
    "avg_kills_per_spawn": 0.897,
    "exp_per_spawn": 169.1,
    "month": "diff_2026_february_march"
  },
  {
    "id": "ussr_t_34_1941_57",
    "mode": "historical",
    "battles": 764938,
    "win_rate": 45.38,
    "avg_kills_per_spawn": 0.844,
    "exp_per_spawn": 199.7,
    "month": "diff_2026_february_march"
  },
  {
    "id": "ussr_t_34_1941_57",
    "mode": "simulation",
    "battles": 5284,
    "win_rate": 58.46,
    "avg_kills_per_spawn": 1.032,
    "exp_per_spawn": 276.3,
    "month": "diff_2026_february_march"
  },
  {
    "id": "ussr_t_34_1941_57",
    "mode": "arcade",
    "battles": 553465,
    "win_rate": 48.03,
    "avg_kills_per_spawn": 0.909,
    "exp_per_spawn": 172.2,
    "month": "diff_2026_january_february"
  },
  {
    "id": "ussr_t_34_1941_57",
    "mode": "historical",
    "battles": 863501,
    "win_rate": 45.01,
    "avg_kills_per_spawn": 0.85,
    "exp_per_spawn": 203.8,
    "month": "diff_2026_january_february"
  },
  {
    "id": "ussr_t_34_1941_57",
    "mode": "simulation",
    "battles": 5443,
    "win_rate": 54.71,
    "avg_kills_per_spawn": 1.021,
    "exp_per_spawn": 282.2,
    "month": "diff_2026_january_february"
  }
]