{
  "id": "bf-109f-4_trop",
  "economy": {
    "researchCost": 13000,
    "purchaseCost": 76000,
    "crewTraining": 22000,
    "expertTraining": 76000,
    "aceTrainingGE": 500,
    "aceTrainingRP": 320000,
    "repairCost": {
      "arcade": [
        982,
        1301
      ],
      "realistic": [
        2223,
        2857
      ],
      "simulator": [
        3309,
        4254
      ]
    },
    "rewardMultiplier": {
      "arcade": 0.59,
      "realistic": 1.47,
      "simulator": 3.08
    },
    "expMultiplier": 1.42
  },
  "weapons": {
    "fixed_weapons": [
      {
        "name": "gunMG17",
        "localizedName": "7.92 жЇ«вЂ‹з±і MG 17 жњєвЂ‹жћЄ",
        "count": 2,
        "bullets": 1000,
        "caliber": 7.9,
        "fireRate": 1200
      },
      {
        "name": "cannonMG15120",
        "localizedName": "20 жЇ«вЂ‹з±і MG 151/20 жњєвЂ‹з‚®",
        "count": 1,
        "bullets": 200,
        "caliber": 20.0,
        "fireRate": 700
      }
    ],
    "payloads": [
      {
        "name": "Bf-109F-4_4xSC50",
        "weapons": [
          {
            "trigger": "bombs",
            "name": "de_sc50",
            "localizedName": "50 еЌѓвЂ‹е…‹ SC50JA з‚ёвЂ‹еј№",
            "count": 1
          },
          {
            "trigger": "bombs",
            "name": "de_sc50",
            "localizedName": "50 еЌѓвЂ‹е…‹ SC50JA з‚ёвЂ‹еј№",
            "count": 1
          },
          {
            "trigger": "bombs",
            "name": "de_sc50",
            "localizedName": "50 еЌѓвЂ‹е…‹ SC50JA з‚ёвЂ‹еј№",
            "count": 1
          },
          {
            "trigger": "bombs",
            "name": "de_sc50",
            "localizedName": "50 еЌѓвЂ‹е…‹ SC50JA з‚ёвЂ‹еј№",
            "count": 1
          }
        ]
      },
      {
        "name": "Bf-109F-4_SC250",
        "weapons": [
          {
            "trigger": "bombs",
            "name": "de_sc250",
            "localizedName": "250 еЌѓвЂ‹е…‹ SC260JA з‚ёвЂ‹еј№",
            "count": 1
          }
        ]
      },
      {
        "name": "Bf-109F-4_flamm_250",
        "weapons": [
          {
            "trigger": "bombs",
            "name": "de_flam_250",
            "localizedName": "Flam C 250 incendiary bomb",
            "count": 1
          }
        ]
      },
      {
        "name": "Bf-109F-4_R1",
        "weapons": [
          {
            "trigger": "additional gun",
            "name": "cannonMG15115_underwing",
            "localizedName": "15 жЇ«вЂ‹з±і MG 151/15 жњєвЂ‹з‚®",
            "count": 125
          },
          {
            "trigger": "additional gun",
            "name": "cannonMG15115_underwing",
            "localizedName": "15 жЇ«вЂ‹з±і MG 151/15 жњєвЂ‹з‚®",
            "count": 125
          }
        ]
      }
    ]
  }
}