{
  "id": "douglas_a_1h",
  "economy": {
    "researchCost": 71000,
    "purchaseCost": 0,
    "purchaseCostGold": 6090,
    "crewTraining": 10000,
    "expertTraining": 340000,
    "aceTrainingGE": 1200,
    "aceTrainingRP": 1180000,
    "repairCost": {
      "arcade": [
        2285,
        2285
      ],
      "realistic": [
        3652,
        3652
      ],
      "simulator": [
        5651,
        5651
      ]
    },
    "rewardMultiplier": {
      "arcade": 2.27,
      "realistic": 4.11,
      "simulator": 12.0
    },
    "expMultiplier": 1.84,
    "freeRepairs": 30
  },
  "weapons": {
    "fixed_weapons": [],
    "payloads": [
      {
        "name": "douglas_a_1h_hvars",
        "weapons": [
          {
            "trigger": "",
            "name": "",
            "localizedName": "",
            "count": 1
          },
          {
            "trigger": "",
            "name": "",
            "localizedName": "",
            "count": 1
          },
          {
            "trigger": "",
            "name": "",
            "localizedName": "",
            "count": 1
          },
          {
            "trigger": "",
            "name": "",
            "localizedName": "",
            "count": 1
          },
          {
            "trigger": "",
            "name": "",
            "localizedName": "",
            "count": 1
          },
          {
            "trigger": "",
            "name": "",
            "localizedName": "",
            "count": 1
          },
          {
            "trigger": "",
            "name": "",
            "localizedName": "",
            "count": 1
          },
          {
            "trigger": "",
            "name": "",
            "localizedName": "",
            "count": 1
          },
          {
            "trigger": "",
            "name": "",
            "localizedName": "",
            "count": 1
          },
          {
            "trigger": "",
            "name": "",
            "localizedName": "",
            "count": 1
          },
          {
            "trigger": "",
            "name": "",
            "localizedName": "",
            "count": 1
          },
          {
            "trigger": "",
            "name": "",
            "localizedName": "",
            "count": 1
          }
        ]
      },
      {
        "name": "douglas_a_1h_aero_6a",
        "weapons": [
          {
            "trigger": "",
            "name": "",
            "localizedName": "",
            "count": 1
          },
          {
            "trigger": "",
            "name": "",
            "localizedName": "",
            "count": 1
          },
          {
            "trigger": "",
            "name": "",
            "localizedName": "",
            "count": 1
          },
          {
            "trigger": "",
            "name": "",
            "localizedName": "",
            "count": 1
          },
          {
            "trigger": "",
            "name": "",
            "localizedName": "",
            "count": 1
          },
          {
            "trigger": "",
            "name": "",
            "localizedName": "",
            "count": 1
          },
          {
            "trigger": "",
            "name": "",
            "localizedName": "",
            "count": 1
          },
          {
            "trigger": "",
            "name": "",
            "localizedName": "",
            "count": 1
          },
          {
            "trigger": "",
            "name": "",
            "localizedName": "",
            "count": 1
          },
          {
            "trigger": "",
            "name": "",
            "localizedName": "",
            "count": 1
          },
          {
            "trigger": "",
            "name": "",
            "localizedName": "",
            "count": 1
          },
          {
            "trigger": "",
            "name": "",
            "localizedName": "",
            "count": 1
          },
          {
            "trigger": "",
            "name": "",
            "localizedName": "",
            "count": 1
          },
          {
            "trigger": "",
            "name": "",
            "localizedName": "",
            "count": 1
          }
        ]
      },
      {
        "name": "douglas_a_1h_aero_7d",
        "weapons": [
          {
            "trigger": "",
            "name": "",
            "localizedName": "",
            "count": 1
          },
          {
            "trigger": "",
            "name": "",
            "localizedName": "",
            "count": 1
          },
          {
            "trigger": "",
            "name": "",
            "localizedName": "",
            "count": 1
          },
          {
            "trigger": "",
            "name": "",
            "localizedName": "",
            "count": 1
          },
          {
            "trigger": "",
            "name": "",
            "localizedName": "",
            "count": 1
          },
          {
            "trigger": "",
            "name": "",
            "localizedName": "",
            "count": 1
          },
          {
            "trigger": "",
            "name": "",
            "localizedName": "",
            "count": 1
          },
          {
            "trigger": "",
            "name": "",
            "localizedName": "",
            "count": 1
          },
          {
            "trigger": "",
            "name": "",
            "localizedName": "",
            "count": 1
          },
          {
            "trigger": "",
            "name": "",
            "localizedName": "",
            "count": 1
          },
          {
            "trigger": "",
            "name": "",
            "localizedName": "",
            "count": 1
          },
          {
            "trigger": "",
            "name": "",
            "localizedName": "",
            "count": 1
          }
        ]
      },
      {
        "name": "douglas_a_1h_lau_10a",
        "weapons": [
          {
            "trigger": "",
            "name": "",
            "localizedName": "",
            "count": 1
          },
          {
            "trigger": "",
            "name": "",
            "localizedName": "",
            "count": 1
          },
          {
            "trigger": "",
            "name": "",
            "localizedName": "",
            "count": 1
          },
          {
            "trigger": "",
            "name": "",
            "localizedName": "",
            "count": 1
          },
          {
            "trigger": "",
            "name": "",
            "localizedName": "",
            "count": 1
          },
          {
            "trigger": "",
            "name": "",
            "localizedName": "",
            "count": 1
          },
          {
            "trigger": "",
            "name": "",
            "localizedName": "",
            "count": 1
          },
          {
            "trigger": "",
            "name": "",
            "localizedName": "",
            "count": 1
          },
          {
            "trigger": "",
            "name": "",
            "localizedName": "",
            "count": 1
          },
          {
            "trigger": "",
            "name": "",
            "localizedName": "",
            "count": 1
          }
        ]
      },
      {
        "name": "douglas_a_1h_30x250lb",
        "weapons": [
          {
            "trigger": "",
            "name": "",
            "localizedName": "",
            "count": 1
          },
          {
            "trigger": "",
            "name": "",
            "localizedName": "",
            "count": 1
          },
          {
            "trigger": "",
            "name": "",
            "localizedName": "",
            "count": 1
          },
          {
            "trigger": "",
            "name": "",
            "localizedName": "",
            "count": 1
          },
          {
            "trigger": "",
            "name": "",
            "localizedName": "",
            "count": 1
          },
          {
            "trigger": "",
            "name": "",
            "localizedName": "",
            "count": 1
          },
          {
            "trigger": "",
            "name": "",
            "localizedName": "",
            "count": 1
          },
          {
            "trigger": "",
            "name": "",
            "localizedName": "",
            "count": 1
          },
          {
            "trigger": "",
            "name": "",
            "localizedName": "",
            "count": 1
          },
          {
            "trigger": "",
            "name": "",
            "localizedName": "",
            "count": 1
          },
          {
            "trigger": "",
            "name": "",
            "localizedName": "",
            "count": 1
          },
          {
            "trigger": "",
            "name": "",
            "localizedName": "",
            "count": 1
          },
          {
            "trigger": "",
            "name": "",
            "localizedName": "",
            "count": 1
          },
          {
            "trigger": "",
            "name": "",
            "localizedName": "",
            "count": 1
          },
          {
            "trigger": "",
            "name": "",
            "localizedName": "",
            "count": 1
          }
        ]
      },
      {
        "name": "douglas_a_1h_30x250lb_snakeye",
        "weapons": [
          {
            "trigger": "",
            "name": "",
            "localizedName": "",
            "count": 1
          },
          {
            "trigger": "",
            "name": "",
            "localizedName": "",
            "count": 1
          },
          {
            "trigger": "",
            "name": "",
            "localizedName": "",
            "count": 1
          },
          {
            "trigger": "",
            "name": "",
            "localizedName": "",
            "count": 1
          },
          {
            "trigger": "",
            "name": "",
            "localizedName": "",
            "count": 1
          },
          {
            "trigger": "",
            "name": "",
            "localizedName": "",
            "count": 1
          },
          {
            "trigger": "",
            "name": "",
            "localizedName": "",
            "count": 1
          },
          {
            "trigger": "",
            "name": "",
            "localizedName": "",
            "count": 1
          },
          {
            "trigger": "",
            "name": "",
            "localizedName": "",
            "count": 1
          },
          {
            "trigger": "",
            "name": "",
            "localizedName": "",
            "count": 1
          },
          {
            "trigger": "",
            "name": "",
            "localizedName": "",
            "count": 1
          },
          {
            "trigger": "",
            "name": "",
            "localizedName": "",
            "count": 1
          },
          {
            "trigger": "",
            "name": "",
            "localizedName": "",
            "count": 1
          },
          {
            "trigger": "",
            "name": "",
            "localizedName": "",
            "count": 1
          },
          {
            "trigger": "",
            "name": "",
            "localizedName": "",
            "count": 1
          }
        ]
      },
      {
        "name": "douglas_a_1h_11x500lb_anm64",
        "weapons": [
          {
            "trigger": "",
            "name": "",
            "localizedName": "",
            "count": 1
          },
          {
            "trigger": "",
            "name": "",
            "localizedName": "",
            "count": 1
          },
          {
            "trigger": "",
            "name": "",
            "localizedName": "",
            "count": 1
          },
          {
            "trigger": "",
            "name": "",
            "localizedName": "",
            "count": 1
          },
          {
            "trigger": "",
            "name": "",
            "localizedName": "",
            "count": 1
          },
          {
            "trigger": "",
            "name": "",
            "localizedName": "",
            "count": 1
          },
          {
            "trigger": "",
            "name": "",
            "localizedName": "",
            "count": 1
          },
          {
            "trigger": "",
            "name": "",
            "localizedName": "",
            "count": 1
          },
          {
            "trigger": "",
            "name": "",
            "localizedName": "",
            "count": 1
          },
          {
            "trigger": "",
            "name": "",
            "localizedName": "",
            "count": 1
          },
          {
            "trigger": "",
            "name": "",
            "localizedName": "",
            "count": 1
          }
        ]
      },
      {
        "name": "douglas_a_1h_18x500lb",
        "weapons": [
          {
            "trigger": "",
            "name": "",
            "localizedName": "",
            "count": 1
          },
          {
            "trigger": "",
            "name": "",
            "localizedName": "",
            "count": 1
          },
          {
            "trigger": "",
            "name": "",
            "localizedName": "",
            "count": 1
          }
        ]
      },
      {
        "name": "douglas_a_1h_18x500lb_snakeye",
        "weapons": [
          {
            "trigger": "",
            "name": "",
            "localizedName": "",
            "count": 1
          },
          {
            "trigger": "",
            "name": "",
            "localizedName": "",
            "count": 1
          },
          {
            "trigger": "",
            "name": "",
            "localizedName": "",
            "count": 1
          }
        ]
      },
      {
        "name": "douglas_a_1h_3x750lb",
        "weapons": [
          {
            "trigger": "",
            "name": "",
            "localizedName": "",
            "count": 1
          },
          {
            "trigger": "",
            "name": "",
            "localizedName": "",
            "count": 1
          },
          {
            "trigger": "",
            "name": "",
            "localizedName": "",
            "count": 1
          }
        ]
      },
      {
        "name": "douglas_a_1h_3x1000lb",
        "weapons": [
          {
            "trigger": "",
            "name": "",
            "localizedName": "",
            "count": 1
          },
          {
            "trigger": "",
            "name": "",
            "localizedName": "",
            "count": 1
          },
          {
            "trigger": "",
            "name": "",
            "localizedName": "",
            "count": 1
          }
        ]
      },
      {
        "name": "douglas_a_1h_3x2000lb",
        "weapons": [
          {
            "trigger": "",
            "name": "",
            "localizedName": "",
            "count": 1
          },
          {
            "trigger": "",
            "name": "",
            "localizedName": "",
            "count": 1
          },
          {
            "trigger": "",
            "name": "",
            "localizedName": "",
            "count": 1
          }
        ]
      },
      {
        "name": "douglas_a_1h_11xmk77",
        "weapons": [
          {
            "trigger": "",
            "name": "",
            "localizedName": "",
            "count": 1
          },
          {
            "trigger": "",
            "name": "",
            "localizedName": "",
            "count": 1
          },
          {
            "trigger": "",
            "name": "",
            "localizedName": "",
            "count": 1
          },
          {
            "trigger": "",
            "name": "",
            "localizedName": "",
            "count": 1
          },
          {
            "trigger": "",
            "name": "",
            "localizedName": "",
            "count": 1
          },
          {
            "trigger": "",
            "name": "",
            "localizedName": "",
            "count": 1
          },
          {
            "trigger": "",
            "name": "",
            "localizedName": "",
            "count": 1
          },
          {
            "trigger": "",
            "name": "",
            "localizedName": "",
            "count": 1
          },
          {
            "trigger": "",
            "name": "",
            "localizedName": "",
            "count": 1
          },
          {
            "trigger": "",
            "name": "",
            "localizedName": "",
            "count": 1
          },
          {
            "trigger": "",
            "name": "",
            "localizedName": "",
            "count": 1
          }
        ]
      },
      {
        "name": "douglas_a_1h_2xblu1",
        "weapons": [
          {
            "trigger": "",
            "name": "",
            "localizedName": "",
            "count": 1
          },
          {
            "trigger": "",
            "name": "",
            "localizedName": "",
            "count": 1
          }
        ]
      },
      {
        "name": "douglas_a_1h_suu_11",
        "weapons": [
          {
            "trigger": "",
            "name": "",
            "localizedName": "",
            "count": 1
          },
          {
            "trigger": "",
            "name": "",
            "localizedName": "",
            "count": 1
          },
          {
            "trigger": "",
            "name": "",
            "localizedName": "",
            "count": 1
          },
          {
            "trigger": "",
            "name": "",
            "localizedName": "",
            "count": 1
          },
          {
            "trigger": "",
            "name": "",
            "localizedName": "",
            "count": 1
          },
          {
            "trigger": "",
            "name": "",
            "localizedName": "",
            "count": 1
          },
          {
            "trigger": "",
            "name": "",
            "localizedName": "",
            "count": 1
          },
          {
            "trigger": "",
            "name": "",
            "localizedName": "",
            "count": 1
          }
        ]
      }
    ]
  }
}