{
  "id": "p-51a_tl",
  "economy": {
    "researchCost": 11000,
    "purchaseCost": 0,
    "purchaseCostGold": 1000,
    "crewTraining": 4800,
    "expertTraining": 32000,
    "aceTrainingGE": 250,
    "aceTrainingRP": 440000,
    "repairCost": {
      "arcade": [
        950,
        950
      ],
      "realistic": [
        884,
        884
      ],
      "simulator": [
        1160,
        1160
      ]
    },
    "rewardMultiplier": {
      "arcade": 1.02,
      "realistic": 2.03,
      "simulator": 4.02
    },
    "expMultiplier": 1.24,
    "freeRepairs": 30
  },
  "weapons": {
    "fixed_weapons": [
      {
        "name": "gunBrowning50_M2",
        "localizedName": "12.7 жЇ«вЂ‹з±і M2 е‹ѓвЂ‹жњ—вЂ‹е®ЃвЂ‹жњєвЂ‹жћЄ",
        "count": 4,
        "bullets": 1260,
        "caliber": 12.7,
        "fireRate": 750
      }
    ],
    "payloads": [
      {
        "name": "p-51a_tl_100lbs",
        "weapons": [
          {
            "trigger": "bombs",
            "name": "us_100lb_anm30",
            "localizedName": "100 зЈ… AN-M30A1 з‚ёвЂ‹еј№",
            "count": 1
          },
          {
            "trigger": "bombs",
            "name": "us_100lb_anm30",
            "localizedName": "100 зЈ… AN-M30A1 з‚ёвЂ‹еј№",
            "count": 1
          }
        ]
      },
      {
        "name": "p-51a_tl_250lbs",
        "weapons": [
          {
            "trigger": "bombs",
            "name": "us_250lb_anm57",
            "localizedName": "250 зЈ… AN-M57 з‚ёвЂ‹еј№",
            "count": 1
          },
          {
            "trigger": "bombs",
            "name": "us_250lb_anm57",
            "localizedName": "250 зЈ… AN-M57 з‚ёвЂ‹еј№",
            "count": 1
          }
        ]
      },
      {
        "name": "p-51a_tl_300lbs",
        "weapons": [
          {
            "trigger": "bombs",
            "name": "us_300lb_m_31",
            "localizedName": "300 lb H.E. M31 bomb",
            "count": 1
          },
          {
            "trigger": "bombs",
            "name": "us_300lb_m_31",
            "localizedName": "300 lb H.E. M31 bomb",
            "count": 1
          }
        ]
      },
      {
        "name": "p-51a_tl_500lbs",
        "weapons": [
          {
            "trigger": "bombs",
            "name": "us_500lb_anm64a1",
            "localizedName": "500 зЈ… AN-M64A1 з‚ёвЂ‹еј№",
            "count": 1
          },
          {
            "trigger": "bombs",
            "name": "us_500lb_anm64a1",
            "localizedName": "500 зЈ… AN-M64A1 з‚ёвЂ‹еј№",
            "count": 1
          }
        ]
      }
    ]
  }
}